{
    "translation": {
      "home": "рд╣реЛрдо",
      "spikeMeme": "рд╕реНрдкрд╛рдЗрдХ рдореЗрдореЗ",
      "degen": "рдбреЗрдЧреЗрди",
      "buySpike": "рд╕реНрдкрд╛рдЗрдХ рдЦрд░реАрджреЗрдВ",
      "nft": "рдПрдирдПрдлрдЯреА",
      "crowd": "рдХреНрд░рд╛рдЙрдб",
      "network": "рдиреЗрдЯрд╡рд░реНрдХ",
      "mainnet": "рдореЗрдирдиреЗрдЯ",
      "testnet": "рдЯреЗрд╕реНрдЯрдиреЗрдЯ",
      "connectWallet": "рд╡реЙрд▓реЗрдЯ рдХрдиреЗрдХреНрдЯ рдХрд░реЗрдВ",
      "disconnect": "рдбрд┐рд╕реНрдХрдиреЗрдХреНрдЯ",
      "trade": "рдЯреНрд░реЗрдб",
      "getFreeSupra": "рдореБрдлреНрдд рд╕реБрдкреНрд░рд╛ рдкреНрд░рд╛рдкреНрдд рдХрд░реЗрдВ",
      "loading": "рд▓реЛрдб рд╣реЛ рд░рд╣рд╛ рд╣реИ...",
      "create": "рдмрдирд╛рдПрдВ",
      "memes": "рдореЗрдореЗрд╕",
      "daos": "рдбреАрдПрдУрдПрд╕",
      "memeFactoryDaoBuilder": "рдореЗрдореЗ рдлреИрдХреНрдЯрд░реА + рдбреАрдПрдУ рдмрд┐рд▓реНрдбрд░ред рдЬрд╣рд╛рдВ рд░рдЪрдирд╛рддреНрдордХрддрд╛ рдмреНрд▓реЙрдХрдЪреЗрди рд╕реЗ рдорд┐рд▓рддреА рд╣реИ! ЁЯЪАтЬи",
      "chatWithSpike": "рд╕реНрдкрд╛рдЗрдХ рдХреЗ рд╕рд╛рде рдЪреИрдЯ рдХрд░реЗрдВ",
      "transactionSuccessful": "рд▓реЗрди-рджреЗрди рд╕рдлрд▓",
      "viewOnExplorer": "рдПрдХреНрд╕рдкреНрд▓реЛрд░рд░ рдкрд░ рджреЗрдЦреЗрдВ",
      "error": "рддреНрд░реБрдЯрд┐",
      "topProjects": "рд╢реАрд░реНрд╖ рдкрд░рд┐рдпреЛрдЬрдирд╛рдПрдВ",
      "search": "рдЦреЛрдЬреЗрдВ",
      "searchForMemes": "рдореЗрдореЗрд╕ рдЦреЛрдЬреЗрдВ...",
      "ticker": "рдЯрд┐рдХрд░",
      "contract": "рдЕрдиреБрдмрдВрдз",
      "red": "рдиреЗрдЯрд╡рд░реНрдХ",
      "supra": "рд╕реБрдкреНрд░рд╛",
      "createdBy": "рджреНрд╡рд╛рд░рд╛ рдмрдирд╛рдпрд╛ рдЧрдпрд╛",
      "spinSpin": "рд╕реНрдкрд┐рди рд╕реНрдкрд┐рди...",
      "buy": " рдЦрд░реАрджреЗрдВ",
      "sell": "рдмреЗрдЪреЗрдВ",
      "balance": "рд╢реЗрд╖ рд░рд╛рд╢рд┐",
      "editPercentages": "рдкреНрд░рддрд┐рд╢рдд рд╕рдВрдкрд╛рджрд┐рдд рдХрд░реЗрдВ",
      "cancel": "рд░рджреНрдж рдХрд░реЗрдВ",
      "save": "рд╕рд╣реЗрдЬреЗрдВ",
      "bondingCurveProgress": "рдмреЙрдиреНрдбрд┐рдВрдЧ рдХрд░реНрд╡ рдкреНрд░рдЧрддрд┐",
      "migrateToDEX": "рдбреАрдИрдПрдХреНрд╕ рдкрд░ рдорд╛рдЗрдЧреНрд░реЗрдЯ рдХрд░реЗрдВ",
      "twitchUnofficial": "ЁЯОе рдЯреНрд╡рд┐рдЪ (рдЕрдиреМрдкрдЪрд╛рд░рд┐рдХ)",
      "hideComments": "рдЯрд┐рдкреНрдкрдгрд┐рдпрд╛рдВ рдЫрд┐рдкрд╛рдПрдВ",
      "showComments": "рдЯрд┐рдкреНрдкрдгрд┐рдпрд╛рдВ рджрд┐рдЦрд╛рдПрдВ",
      "amount": "рд░рд╛рд╢рд┐",
      "collapse": "рд╕рдВрдХреНрд╖рд┐рдкреНрдд рдХрд░реЗрдВ",
      "expand": "рд╡рд┐рд╕реНрддрд╛рд░ рдХрд░реЗрдВ",
      "contractLabel": "рдЕрдиреБрдмрдВрдз",
      "created": "рдмрдирд╛рдпрд╛ рдЧрдпрд╛",
      "serverError": "рд╕рд░реНрд╡рд░ рддреНрд░реБрдЯрд┐...",
      "timeIsUp": "рд╕рдордп рд╕рдорд╛рдкреНрдд!",
      "months": "рдорд╣реАрдиреЗ",
      "days": "рджрд┐рди",
      "hours": "рдШрдВрдЯреЗ",
      "minutes": "рдорд┐рдирдЯ",
      "seconds": "рд╕реЗрдХрдВрдб",
      "airdrop": "рдПрдпрд░рдбреНрд░реЙрдк",
      "sellFee": "рдмрд┐рдХреНрд░реА рд╢реБрд▓реНрдХ",
      "firstNFTCollection": "рд╕реБрдкреНрд░рд╛ рдкрд░ рдкрд╣рд▓рд╛ рдПрдирдПрдлрдЯреА рд╕рдВрдЧреНрд░рд╣",
      "copy": "рдХреЙрдкреА",
      "price": "рдХреАрдордд",
      "minting": "рдорд┐рдВрдЯрд┐рдВрдЧ...",
      "mintYourNFT": "рдЕрдкрдирд╛ рдПрдирдПрдлрдЯреА рдорд┐рдВрдЯ рдХрд░реЗрдВ",
      "minted": "рдорд┐рдВрдЯ рдХрд┐рдпрд╛ рдЧрдпрд╛",
      "successfulTransaction": "рд╕рдлрд▓ рд▓реЗрди-рджреЗрди!",
      "transactionProcessed": "рдЖрдкрдХрд╛ рд▓реЗрди-рджреЗрди рд╕рдлрд▓рддрд╛рдкреВрд░реНрд╡рдХ рд╕рдВрд╕рд╛рдзрд┐рдд рд╣реЛ рдЧрдпрд╛ рд╣реИред",
      "txHash": "TX рд╣реИрд╢",
      "noTransactionYet": "рдЕрднреА рддрдХ рдХреЛрдИ рд▓реЗрди-рджреЗрди рдирд╣реАрдВ",
      "close": "рдмрдВрдж рдХрд░реЗрдВ",
      "spikeCrowdfunding": "рд╕реНрдкрд╛рдЗрдХ рдХреНрд░рд╛рдЙрдбрдлрдВрдбрд┐рдВрдЧ",
      "crowdDescription": "рд╕реБрдкреНрд░рд╛ рдиреЗрдЯрд╡рд░реНрдХ рдкрд░ рд╕реНрдкрд╛рдЗрдХ рдХреЗ рд▓рд┐рдП рдПрдПрдордПрдо рдФрд░ рд▓реЙрдиреНрдЪрд░ рдкреИрдб рдЕрдиреБрдмрдВрдзреЛрдВ рдХрд╛ рдСрдбрд┐рдЯ рдХрд░рдиреЗ рдореЗрдВ рдорджрдж рдХрд░реЗрдВ! рдмреАрдЯреАрд╕реА, рдмреАрдПрдирдмреА, рд╕реЛрд▓рд╛рдирд╛, рдИрд╡реАрдПрдо, рдпрд╛ рд╕реБрдкреНрд░рд╛ рдореЗрдВ рджрд╛рди рдХрд░реЗрдВ рдФрд░ рд╕реНрдкрд╛рдЗрдХ рдСрдбрд┐рд╢рди рдореЗрдВ рд╢рд╛рдорд┐рд▓ рд╣реЛрдВред ЁЯЪА",
      "target": "рд▓рдХреНрд╖реНрдп",
      "contractAudited": "рдЕрдиреБрдмрдВрдз рдСрдбрд┐рдЯ рдХрд┐рдпрд╛ рдЧрдпрд╛",
      "raised": "рдЬреБрдЯрд╛рдпрд╛ рдЧрдпрд╛",
      "goal": "рд▓рдХреНрд╖реНрдп",
      "multiChainDonationAddresses": "рдорд▓реНрдЯреА-рдЪреЗрди рджрд╛рди рдкрддреЗ",
      "solana": "рд╕реЛрд▓рд╛рдирд╛",
      "eth": "рдИрдЯреАрдПрдЪ",
      "btc": "рдмреАрдЯреАрд╕реА",
      "bnb": "рдмреАрдПрдирдмреА",
      "BTC": "рдмреАрдЯреАрд╕реА",
      "BNB": "рдмреАрдПрдирдмреА",
      "donateSupra": "рд╕реБрдкреНрд░рд╛ рджрд╛рди рдХрд░реЗрдВ",
      "enterAmount": "рд░рд╛рд╢рд┐ рджрд░реНрдЬ рдХрд░реЗрдВ",
      "donate": "рджрд╛рди рдХрд░реЗрдВ",
      "claimRewards": "рдкреБрд░рд╕реНрдХрд╛рд░реЛрдВ рдХрд╛ рджрд╛рд╡рд╛ рдХрд░реЗрдВ",
      "rewardsAvailableIn": "рдкреБрд░рд╕реНрдХрд╛рд░ рдЗрд╕рдореЗрдВ рдЙрдкрд▓рдмреНрдз рд╣реЛрдВрдЧреЗ:",
      "rewardsAvailableNow": "рдкреБрд░рд╕реНрдХрд╛рд░ рдЕрдм рдЙрдкрд▓рдмреНрдз рд╣реИрдВ!",
      "claimLocked": "рджрд╛рд╡рд╛ рдмрдВрдж",
      "claimRewardsButton": "рдкреБрд░рд╕реНрдХрд╛рд░реЛрдВ рдХрд╛ рджрд╛рд╡рд╛ рдХрд░реЗрдВ",
      "success": "рд╕рдлрд▓рддрд╛!",
      "joinedSpikeMission": "рдЖрдк рд╕реНрдкрд╛рдЗрдХ рдорд┐рд╢рди рдореЗрдВ рд╢рд╛рдорд┐рд▓ рд╣реЛ рдЧрдП рд╣реИрдВ!",
      "viewTransaction": "рд▓реЗрди-рджреЗрди рджреЗрдЦреЗрдВ",
      "rewardsClaimed": "рдкреБрд░рд╕реНрдХрд╛рд░реЛрдВ рдХрд╛ рджрд╛рд╡рд╛ рдХрд┐рдпрд╛ рдЧрдпрд╛!",
      "cosmicTokensYours": "рдЖрдкрдХреЗ рдмреНрд░рд╣реНрдорд╛рдВрдбреАрдп рдЯреЛрдХрди рдЖрдкрдХреЗ рд╣реИрдВ!",
      "fetchError": "рддреНрд░реБрдЯрд┐ рдкреНрд░рд╛рдкреНрдд рдХрд░реЗрдВ",
      "loadingInfo": "рдкреВрд▓ рдЬрд╛рдирдХрд╛рд░реА рд▓реЛрдб рд╣реЛ рд░рд╣реА рд╣реИ...",
      "poolInfoUnavailable": "рдЗрд╕ рдкреВрд▓ рдХреЗ рд▓рд┐рдП рдЯрд┐рдкреНрдкрдгреА рдЕрдиреБрднрд╛рдЧ рдЕрдиреБрдкрд▓рдмреНрдз рд╣реИред",
      "loadingProjectInfo": "рдореЗрдореЗ рдЬрд╛рдирдХрд╛рд░реА рд▓реЛрдб рд╣реЛ рд░рд╣реА рд╣реИ...",
      "yourBalance": "рдЖрдкрдХреА рд╢реЗрд╖ рд░рд╛рд╢рд┐",
      "staked": "рд╕реНрдЯреЗрдХ рдХрд┐рдпрд╛ рдЧрдпрд╛",
      "maxSupply": "рдЕрдзрд┐рдХрддрдо рдЖрдкреВрд░реНрддрд┐",
      "stake": "рд╕реНрдЯреЗрдХ",
      "unstake": "рдЕрдирд╕реНрдЯреЗрдХ",
      "stakePrompt": "рдкреБрд░рд╕реНрдХрд╛рд░ рдЕрд░реНрдЬрд┐рдд рдХрд░рдиреЗ рдФрд░ рдкрд░рд┐рдпреЛрдЬрдирд╛ рдХрд╛ рд╕рдорд░реНрдерди рдХрд░рдиреЗ рдХреЗ рд▓рд┐рдП рдЕрдкрдиреЗ рдЯреЛрдХрди рд╕реНрдЯреЗрдХ рдХрд░реЗрдВ!",
      "amountToStake": "рд╕реНрдЯреЗрдХ рдХрд░рдиреЗ рдХреЗ рд▓рд┐рдП рд░рд╛рд╢рд┐",
      "max": "рдЕрдзрд┐рдХрддрдо",
      "unstakePrompt": "рдЙрдиреНрд╣реЗрдВ рд╕реНрдЯреЗрдХрд┐рдВрдЧ рдкреВрд▓ рд╕реЗ рдирд┐рдХрд╛рд▓рдиреЗ рдХреЗ рд▓рд┐рдП рдЕрдкрдиреЗ рдЯреЛрдХрди рдЕрдирд╕реНрдЯреЗрдХ рдХрд░реЗрдВред",
      "amountToUnstake": "рдЕрдирд╕реНрдЯреЗрдХ рдХрд░рдиреЗ рдХреЗ рд▓рд┐рдП рд░рд╛рд╢рд┐",
      "confirmStake": "рд╕реНрдЯреЗрдХ рдХреА рдкреБрд╖реНрдЯрд┐ рдХрд░реЗрдВ",
      "unstakeAll": "рд╕рднреА рдЕрдирд╕реНрдЯреЗрдХ рдХрд░реЗрдВ",
      "emergencyUnstakeInfo": "рдпрд╣ рдПрдХ рдЖрдкрд╛рддрдХрд╛рд▓реАрди рдЕрдирд╕реНрдЯреЗрдХрд┐рдВрдЧ рдЯреЛрдХрди рд╣реИред рдЖрдк рдПрдХ рдмрд╛рд░ рдореЗрдВ рдЕрдкрдиреЗ рд╕рднреА рдлрдВрдб рдирд┐рдХрд╛рд▓ рд╕рдХрддреЗ рд╣реИрдВред",
      "confirmUnstake": "рдЕрдирд╕реНрдЯреЗрдХ рдХреА рдкреБрд╖реНрдЯрд┐ рдХрд░реЗрдВ",
      "yourStake": "рдЖрдкрдХрд╛ рд╕реНрдЯреЗрдХ",
      "hodlNow": "рд╣реЛрдбрд▓!!!",
      "hodlVaultDescription": "рдкрд░рд┐рдпреЛрдЬрдирд╛ рдореЗрдВ рд╕рдорд░реНрдерди рджрд┐рдЦрд╛рдиреЗ рдФрд░ рд╡рд┐рд╢реНрд╡рд╛рд╕ рдмрдирд╛рдиреЗ рдХреЗ рд▓рд┐рдП рдЕрдкрдиреЗ рдЯреЛрдХрди рд╣реЛрдбрд▓ рдХрд░реЗрдВред",
      "hodlVaultVesting": "рд╕реНрдЯреЗрдХ рдХрд┐рдП рдЧрдП рдЯреЛрдХрди {count, plural, =1 {# рдорд╣реАрдиреЗ} other {# рдорд╣реАрдиреЗ}} рдХреА рдЕрд╡рдзрд┐ рдореЗрдВ рдзреАрд░реЗ-рдзреАрд░реЗ рдЕрдирд▓реЙрдХ рд╣реЛрддреЗ рд╣реИрдВред рдЖрдк рдХрд┐рд╕реА рднреА рд╕рдордп рдЕрдкрдиреЗ рдЕрдирд▓реЙрдХ рдХрд┐рдП рдЧрдП рд╣рд┐рд╕реНрд╕реЗ рдХреЛ рдирд┐рдХрд╛рд▓ рд╕рдХрддреЗ рд╣реИрдВред",
      "availableToStake": "рд╕реНрдЯреЗрдХ рдХреЗ рд▓рд┐рдП рдЙрдкрд▓рдмреНрдз",
      "totalStaked": "рдХреБрд▓ рд╕реНрдЯреЗрдХ рдХрд┐рдпрд╛ рдЧрдпрд╛",
      "availableToUnstake": "рдЕрдирд╕реНрдЯреЗрдХ рдХреЗ рд▓рд┐рдП рдЙрдкрд▓рдмреНрдз",
      "collapseDetails": "рд╡рд┐рд╡рд░рдг рд╕рдВрдХреНрд╖рд┐рдкреНрдд рдХрд░реЗрдВ",
      "expandDetails": "рд╡рд┐рд╡рд░рдгр╕Вр╕вр╕▓р╕в",
      "noDescription": "рдХреЛрдИ рд╡рд┐рд╡рд░рдг рдирд╣реАрдВ... рдХреНрдпреЛрдВрдХрд┐ рдореЗрдореЗ рдЦреБрдж рдмреЛрд▓рддрд╛ рд╣реИ (рдпрд╛ рдирд┐рд░реНрдорд╛рддрд╛ рд╕рд┐рд░реНрдл рдЖрд▓рд╕реА рдерд╛)ред =)",
      "maxAvailable": "рдЕрдзрд┐рдХрддрдо рдЙрдкрд▓рдмреНрдз",
      "processing": "рд╕рдВрд╕рд╛рдзрд┐рдд рд╣реЛ рд░рд╣рд╛ рд╣реИ...",
      "stakeSuccessTitle": "рд╕реНрдЯреЗрдХ рд╕рдлрд▓",
      "unstakeSuccessTitle": "рдЕрдирд╕реНрдЯреЗрдХ рд╕рдлрд▓",
      "emergencyUnstakeSuccessTitle": "рдЖрдкрд╛рддрдХрд╛рд▓реАрди рдЕрдирд╕реНрдЯреЗрдХ рд╕рдлрд▓",
      "unknownError": "рдПрдХ рдЕрдЬреНрдЮрд╛рдд рддреНрд░реБрдЯрд┐ рд╣реБрдИред",
      "ProjectNotFound": "рдореЗрдореЗ рдирд╣реАрдВ рдорд┐рд▓рд╛ред",
      "stakingDuration": "рд╣реЛрдбрд▓ рдЕрд╡рдзрд┐",
      "unstakePeriodMonths": "рдорд╣реАрдиреЗ",
      "hodlPeriod": "{count, plural, =1 {# рдорд╣реАрдиреЗ рдХрд╛ рд▓реЙрдХ} other {# рдорд╣реАрдиреЗ рдХрд╛ рд▓реЙрдХ}}",
      "dragAndDropOrClick": "рдЦреАрдВрдЪреЗрдВ рдФрд░ рдЫреЛрдбрд╝реЗрдВ рдпрд╛ рдХреНрд▓рд┐рдХ рдХрд░реЗрдВ",
      "selectTokenPrompt": "рдЯреЛрдХрди рдЪреБрдиреЗрдВред",
      "fileTooLarge": "рдлрд╝рд╛рдЗрд▓ рдмрд╣реБрдд рдмрдбрд╝реА рд╣реИ (рдЕрдзрд┐рдХрддрдо 1MB)",
      "holdToSwitch": "{networkName} рдкрд░ рд╕реНрд╡рд┐рдЪ рдХрд░рдиреЗ рдХреЗ рд▓рд┐рдП {seconds} рдХреЗ рд▓рд┐рдП рджрдмрд╛рдП рд░рдЦреЗрдВ",
      "testnetShort": "рдЯреЗрд╕реНрдЯрдиреЗрдЯ",
      "page": "рдкреГрд╖реНрда",
      "previous": "рдкрд┐рдЫрд▓рд╛",
      "next": "рдЕрдЧрд▓рд╛",
      "noResultsFound": "рдХреЛрдИ рдкрд░рд┐рдгрд╛рдо рдирд╣реАрдВ рдорд┐рд▓рд╛ред",
      "searching": "рдЦреЛрдЬ рд░рд╣рд╛ рд╣реИ",
      "networkMismatchError": "рдЯрд┐рдкреНрдкрдгреА рдХрд░рдиреЗ рдХреЗ рд▓рд┐рдП рдХреГрдкрдпрд╛ {networkName} рдиреЗрдЯрд╡рд░реНрдХ рдкрд░ рд╕реНрд╡рд┐рдЪ рдХрд░реЗрдВред",
      "allCategories": "рд╕рднреА",
      "poolCompletedTitle": "рдкреВрд▓ рдкреВрд░рд╛ рд╣реБрдЖ",
      "poolCompletedSubtitle": "рдбреАрдИрдПрдХреНрд╕ рдкрд░ рдорд╛рдЗрдЧреНрд░реЗрдЯ рдХрд░реЗрдВ",
      "nameLabel": "рдирд╛рдо",
      "congrats": "рдмрдзрд╛рдИ рд╣реЛ",
      "coinBorn": "рдЖрдкрдХрд╛ рдЯреЛрдХрди рдкреИрджрд╛ рд╣реБрдЖ рд╣реИ",
      "migrationTitle": "рдорд╛рдЗрдЧреНрд░реЗрд╢рди рдкреВрд░рд╛ рд╣реБрдЖ",
      "migrationPanelDescription": "рдЕрдм рдЙрдкрд▓рдмреНрдз рд╣реИ:",
      "runManualMigration": "рдорд╛рдЗрдЧреНрд░реЗрд╢рди рдЪрд▓рд╛рдПрдВ",
      "poolCompleted": "рдкреВрд▓ рдкреВрд░рд╛ рд╣реБрдЖ",
      "mainnetShort": "рдореЗрдирдиреЗрдЯ",
      "topHolders": "рд╢реАрд░реНрд╖ рдзрд╛рд░рдХ",
      "wallet": "рд╡реЙрд▓реЗрдЯ",
      "quantity": "рдорд╛рддреНрд░рд╛",
      "noHoldersFound": "рдХреЛрдИ рдзрд╛рд░рдХ рдирд╣реАрдВ рдорд┐рд▓рд╛ред",
      "loadingChart": "рдЪрд╛рд░реНрдЯ рд▓реЛрдб рд╣реЛ рд░рд╣рд╛ рд╣реИ...",
      "chartError": "рдЪрд╛рд░реНрдЯ рдбреЗрдЯрд╛ рд▓реЛрдб рдХрд░рдиреЗ рдореЗрдВ рддреНрд░реБрдЯрд┐ред",
      "copyAddress": "рдкрддрд╛ рдХреЙрдкреА рдХрд░реЗрдВ",
      "countdown": {
        "completed": "рдШрдЯрдирд╛ рдпрд╣рд╛рдБ рд╣реИ!",
        "days": "рджрд┐рди",
        "hours": "рдШрдВрдЯреЗ",
        "minutes": "рдорд┐рдирдЯ",
        "seconds": "рд╕реЗрдХрдВрдб",
        "spikeyChamp": "Spikey Champ"
      },
      "popup": {
        "create_button": "рдмрдирд╛рдПрдВ",
        "sending_transaction": "tx рднреЗрдЬ рд░рд╣рд╛ рд╣реИ",
        "creating": "рдмрдирд╛ рд░рд╣рд╛ рд╣реИ...",
        "uploading_files": "рдореЗрдЯрд╛рдбреЗрдЯрд╛ рдЕрдкрд▓реЛрдб рдХрд░ рд░рд╣рд╛ рд╣реИ",
        "uploading_image": "рдЫрд╡рд┐ рдЕрдкрд▓реЛрдб рдХрд░ рд░рд╣рд╛ рд╣реИ (1/3)...",
        "uploading_metadata": "рдореЗрдЯрд╛рдбреЗрдЯрд╛ рд╕рд╣реЗрдЬ рд░рд╣рд╛ рд╣реИ (2/3)...",
        "polling_for_address": "рдкрддрд╛ рдкреНрд░рд╛рдкреНрдд рдХрд░ рд░рд╣рд╛ рд╣реИ",
        "creating_contract": "рдСрди-рдЪреЗрди рдкреНрд░реЛрдЬреЗрдХреНрдЯ рдмрдирд╛ рд░рд╣рд╛ рд╣реИ (3/3)...",
        "creationFee": "рд╢реБрд▓реНрдХ: ${usd} (~{supra} SUPRA)"
      },
      "disclaimer": {
        "title": "рдЪреЗрддрд╛рд╡рдиреА! ЁЯЪи рдпрд╣ Spikey.fun рд╣реИ - рд╡реЙрд▓ рд╕реНрдЯреНрд░реАрдЯ рдирд╣реАрдВред",
        "intro": "рдпрд╣ рдкреНрд▓реЗрдЯрдлреЙрд░реНрдо рдореЗрдореЗ, рд╕рдкрдиреЛрдВ рдФрд░ рдбреАрдЬреЗрдирд░реЗрдЯ рд╕реЗ рднрд░рд╛ рд╣реИред рдпрд╣рд╛рдВ рдХреЛрдИ рднреА рдЯреЛрдХрди рд▓реЙрдиреНрдЪ рдХрд░ рд╕рдХрддрд╛ рд╣реИред рдЗрд╕рдореЗрдВ рдЖрдкрдХреА рджрд╛рджреА, рдЖрдкрдХрд╛ рдХреБрддреНрддрд╛, рдпрд╛ рдПрдХ рд╡рд╛рд╕реНрддрд╡рд┐рдХ рд╣реЗрдЬрд╣реЛрдЧ рд╢рд╛рдорд┐рд▓ рд╣реИред",
        "listTitle": "Spikey.fun рдкрд░ рдмрдирд╛рдП рдЧрдП рдЯреЛрдХрди рд╣реИрдВ:",
        "listItem1": "ЁЯзк рдкреНрд░рд╛рдпреЛрдЧрд┐рдХ",
        "listItem2": "ЁЯз╗ рдЗрд▓рд┐рдХреНрд╡рд┐рдб",
        "listItem3": "ЁЯза рдЕрдХреНрд╕рд░ рдореВрд░реНрдЦ (рд▓реЗрдХрд┐рди рдХрднреА-рдХрднреА рдкреНрд░рддрд┐рднрд╛рд╢рд╛рд▓реА)",
        "listItem4": "ЁЯжФ рд╕реНрдкрд╛рдЗрдХреА-рдЕрдиреБрдореЛрджрд┐рдд (рдмрд╕ рдордЬрд╛рдХ рдХрд░ рд░рд╣рд╛ рд╣реВрдВ, рдХреБрдЫ рднреА рдирд╣реАрдВ рд╣реИ)",
        "warning": "рдпрд╣рд╛рдВ рдЯреЛрдХрди рдЦрд░реАрджрдирд╛ рдПрдХ рдЬрдВрдЧрд▓реА рд╣реЗрдЬрд╣реЛрдЧ рдХреЛ рдкрд╛рд▓рддреВ рдмрдирд╛рдиреЗ рдЬреИрд╕рд╛ рд╣реИ - рдпрд╣ рдордЬреЗрджрд╛рд░ рд╣реЛ рд╕рдХрддрд╛ рд╣реИ, рдпрд╛ рдЖрдкрдХреЛ рдЪреБрдн рд╕рдХрддрд╛ рд╣реИред",
        "dyor": "рдХреГрдкрдпрд╛ рдХреБрдЫ рднреА рдЫреВрдиреЗ рд╕реЗ рдкрд╣рд▓реЗ рдЕрдкрдирд╛ рдЦреБрдж рдХрд╛ рд╢реЛрдз рдХрд░реЗрдВ (DYOR)ред",
        "loseFunds": "рдпрджрд┐ рдЖрдк рдЕрдкрдиреЗ рдлрдВрдб рдЦреЛ рджреЗрддреЗ рд╣реИрдВ, рддреЛ рд╕реНрдкрд╛рдЗрдХреА рджреБрдЦреА рд╣реЛрдЧрд╛, рд▓реЗрдХрд┐рди рдЬрд┐рдореНрдореЗрджрд╛рд░ рдирд╣реАрдВ рд╣реЛрдЧрд╛ред",
        "winFunds": "рдпрджрд┐ рдЖрдк рдПрдХ рдореЗрдореЗрд▓рд┐рдпрди рдмрди рдЬрд╛рддреЗ рд╣реИрдВ, рддреЛ рд╕реНрдкрд╛рдЗрдХреА рдЖрдкрдХреА рдирд╛рдХ рдкрд░ рдердкрдердкрд╛ рд╕рдХрддрд╛ рд╣реИред",
        "acceptButton": "рдореИрдВ рд╕рдордЭрддрд╛ рд╣реВрдВ рдФрд░ рд╕реНрд╡реАрдХрд╛рд░ рдХрд░рддрд╛ рд╣реВрдВ"
      },
      "retry": "рдкреБрдирдГ рдкреНрд░рдпрд╛рд╕ рдХрд░реЗрдВ"
    },
    "wallets": {
      "connected": "рдХрдиреЗрдХреНрдЯреЗрдб",
      "title": "рд╡реЙрд▓реЗрдЯ рдХрдиреЗрдХреНрдЯ рдХрд░реЗрдВ",
      "closeButtonLabel": "рдмрдВрдж рдХрд░реЗрдВ",
      "description": "рдЬрд╛рд░реА рд░рдЦрдиреЗ рдХреЗ рд▓рд┐рдП рдЕрдкрдирд╛ рд╡реЙрд▓реЗрдЯ рдХрдиреЗрдХреНрдЯ рдХрд░реЗрдВ"
    },
    "comments": {
      "title": "рдЯрд┐рдкреНрдкрдгрд┐рдпрд╛рдВ",
      "addCommentPlaceholder": "рдПрдХ рдЯрд┐рдкреНрдкрдгреА рдЬреЛрдбрд╝реЗрдВ...",
      "uploadMediaTitle": "рдЫрд╡рд┐/рд╡реАрдбрд┐рдпреЛ рдЕрдкрд▓реЛрдб рдХрд░реЗрдВ",
      "posting": "рдкреЛрд╕реНрдЯ рдХрд░ рд░рд╣рд╛ рд╣реИ...",
      "postButton": "рдкреЛрд╕реНрдЯ",
      "removeMediaTitle": "рдореАрдбрд┐рдпрд╛ рд╣рдЯрд╛рдПрдВ",
      "connectWalletError": "!рд╡реЙрд▓реЗрдЯ рдХрдиреЗрдХреНрдЯ рдХрд░реЗрдВ!",
      "missingInfoError": "рдЕрдиреБрдмрдВрдз рдпрд╛ рдиреЗрдЯрд╡рд░реНрдХ рдЬрд╛рдирдХрд╛рд░реА рдЧрд╛рдпрдм рд╣реИред",
      "emptyCommentError": "рдЦрд╛рд▓реА рдЯрд┐рдкреНрдкрдгреА рдкреЛрд╕реНрдЯ рдирд╣реАрдВ рдХреА рдЬрд╛ рд╕рдХрддреАред",
      "unknownError": "рдПрдХ рдЕрдЬреНрдЮрд╛рдд рддреНрд░реБрдЯрд┐ рд╣реБрдИред",
      "loading": "рдЯрд┐рдкреНрдкрдгрд┐рдпрд╛рдВ рд▓реЛрдб рд╣реЛ рд░рд╣реА рд╣реИрдВ...",
      "noComments": "рдЕрднреА рддрдХ рдХреЛрдИ рдЯрд┐рдкреНрдкрдгреА рдирд╣реАрдВред",
      "loadingInfo": "рдкреВрд▓ рдЬрд╛рдирдХрд╛рд░реА рд▓реЛрдб рд╣реЛ рд░рд╣реА рд╣реИ...",
      "poolInfoUnavailable": "рдЗрд╕ рдкреВрд▓ рдХреЗ рд▓рд┐рдП рдЯрд┐рдкреНрдкрдгреА рдЕрдиреБрднрд╛рдЧ рдЕрдиреБрдкрд▓рдмреНрдз рд╣реИред",
      "fetchError": "рдЯрд┐рдкреНрдкрдгрд┐рдпрд╛рдВ рдкреНрд░рд╛рдкреНрдд рдХрд░рдиреЗ рдореЗрдВ рддреНрд░реБрдЯрд┐",
      "nonceLoadErrorRetry": "рд╕рддреНрдпрд╛рдкрди рдбреЗрдЯрд╛ рд▓реЛрдб рдирд╣реАрдВ рдХрд┐рдпрд╛ рдЬрд╛ рд╕рдХрд╛ред рдХреГрдкрдпрд╛ рдкреБрдирдГ рдкреНрд░рдпрд╛рд╕ рдХрд░реЗрдВред",
      "connectWalletPrompt": "рдЯрд┐рдкреНрдкрдгреА рдХрд░рдиреЗ рдХреЗ рд▓рд┐рдП рд╡реЙрд▓реЗрдЯ рдХрдиреЗрдХреНрдЯ рдХрд░реЗрдВ",
      "signingFailedOrCancelled": "рд╣рд╕реНрддрд╛рдХреНрд╖рд░ рд╡рд┐рдлрд▓ рдпрд╛ рд░рджреНрдж",
      "connectWallet": "рд╡реЙрд▓реЗрдЯ рдХрдиреЗрдХреНрдЯ рдХрд░реЗрдВ",
      "connectToComment": "рдЯрд┐рдкреНрдкрдгреА рдХрд░рдиреЗ рдХреЗ рд▓рд┐рдП рд╡реЙрд▓реЗрдЯ рдХрдиреЗрдХреНрдЯ рдХрд░реЗрдВ",
      "likeCount": "{count, plural, =0 {0 рд▓рд╛рдЗрдХ} =1 {1 рд▓рд╛рдЗрдХ} other {# рд▓рд╛рдЗрдХ}}",
      "beTheFirst": "рдЯрд┐рдкреНрдкрдгреА рдХрд░рдиреЗ рд╡рд╛рд▓реЗ рдкрд╣рд▓реЗ рд╡реНрдпрдХреНрддрд┐ рдмрдиреЗрдВ",
      "nonceFetchError": "рдиреЛрдВрд╕ рдкреНрд░рд╛рдкреНрдд рдХрд░рдиреЗ рдореЗрдВ рддреНрд░реБрдЯрд┐ред рдХреГрдкрдпрд╛ рдмрд╛рдж рдореЗрдВ рдкреБрдирдГ рдкреНрд░рдпрд╛рд╕ рдХрд░реЗрдВред"
    },
    "Footer": {
      "brandName": "рд╕реНрдкрд╛рдЗрдХреА рдХреЙрд░реНрдк",
      "copyright": "┬й {year} рд╕реНрдкрд╛рдЗрдХреА рдХреЙрд░реНрдкред рд╕рд░реНрд╡рд╛рдзрд┐рдХрд╛рд░ рд╕реБрд░рдХреНрд╖рд┐рддред",
      "explore": "рдЕрдиреНрд╡реЗрд╖рдг рдХрд░реЗрдВ",
      "community": "рд╕рдореБрджрд╛рдп рдореЗрдВ рд╢рд╛рдорд┐рд▓ рд╣реЛрдВ",
      "whitepaper": "рд╢реНрд╡реЗрддрдкрддреНрд░",
      "terms": "рд╕реЗрд╡рд╛ рдХреА рд╢рд░реНрддреЗрдВ",
      "privacy": "рдЧреЛрдкрдиреАрдпрддрд╛ рдиреАрддрд┐",
      "secretTooltip": "рдпрд╣ рдХреНрдпрд╛ рд╣реИ?",
      "secretTooltip2": "рдЬрд╛рд░реА рд░рдЦреЗрдВ...",
      "secretTooltip3": "рдПрдХ рдмрд╛рд░ рдФрд░!"
    }
}