{
    "translation": {
      "home": "ホーム",
      "spikeMeme": "SPIKEミーム",
      "degen": "Degen",
      "buySpike": "Spikeを購入",
      "nft": "NFT",
      "crowd": "クラウド",
      "network": "ネットワーク",
      "mainnet": "メインネット",
      "testnet": "テストネット",
      "connectWallet": "ウォレットを接続",
      "disconnect": "切断",
      "trade": "トレード",
      "getFreeSupra": "無料のSUPRAを入手",
      "loading": "読み込み中...",
      "create": "作成",
      "memes": "ミーム",
      "daos": "DAO",
      "memeFactoryDaoBuilder": "ミームファクトリー+ DAOビルダー。創造性がブロックチェーンと出会う場所！🚀✨",
      "chatWithSpike": "Spikeとチャット",
      "transactionSuccessful": "取引成功",
      "viewOnExplorer": "エクスプローラーで表示",
      "error": "エラー",
      "topProjects": "トッププロジェクト",
      "search": "検索",
      "searchForMemes": "ミームを検索...",
      "ticker": "ティッカー",
      "contract": "契約",
      "red": "ネットワーク",
      "supra": "Supra",
      "createdBy": "作成者",
      "spinSpin": "スピン スピン...",
      "buy": "購入",
      "sell": "売却",
      "balance": "残高",
      "editPercentages": "パーセンテージを編集",
      "cancel": "キャンセル",
      "save": "保存",
      "bondingCurveProgress": "ボンディングカーブの進捗",
      "migrateToDEX": "DEXに移行",
      "twitchUnofficial": "🎥 TWITCH (非公式)",
      "hideComments": "コメントを非表示",
      "showComments": "コメントを表示",
      "amount": "金額",
      "collapse": "折りたたむ",
      "expand": "展開",
      "contractLabel": "契約",
      "created": "作成日",
      "serverError": "サーバーエラー...",
      "timeIsUp": "時間切れです！",
      "months": "ヶ月",
      "days": "日",
      "hours": "時間",
      "minutes": "分",
      "seconds": "秒",
      "airdrop": "エアドロップ",
      "sellFee": "売却手数料",
      "firstNFTCollection": "Supra初のNFTコレクション",
      "copy": "コピー",
      "price": "価格",
      "minting": "ミント中...",
      "mintYourNFT": "NFTをミント",
      "minted": "ミント済み",
      "successfulTransaction": "取引成功！",
      "transactionProcessed": "取引は正常に処理されました。",
      "txHash": "TXハッシュ",
      "noTransactionYet": "まだ取引はありません",
      "close": "閉じる",
      "spikeCrowdfunding": "Spikeクラウドファンディング",
      "crowdDescription": "Supraネットワーク上のSpikeのAMMおよびランチャーパッド契約の監査にご協力ください！BTC、BNB、Solana、EVM、またはSupraで寄付し、Spikeオーディションにご参加ください。🚀",
      "target": "目標",
      "contractAudited": "契約監査済み",
      "raised": "調達額",
      "goal": "目標",
      "multiChainDonationAddresses": "マルチチェーン寄付アドレス",
      "solana": "Solana",
      "eth": "ETH",
      "btc": "BTC",
      "bnb": "BNB",
      "BTC": "BTC",
      "BNB": "BNB",
      "donateSupra": "SUPRAを寄付",
      "enterAmount": "金額を入力",
      "donate": "寄付",
      "claimRewards": "報酬を請求",
      "rewardsAvailableIn": "報酬は次の期間に利用可能になります：",
      "rewardsAvailableNow": "報酬が利用可能になりました！",
      "claimLocked": "請求はロックされています",
      "claimRewardsButton": "報酬を請求",
      "success": "成功！",
      "joinedSpikeMission": "Spikeミッションに参加しました！",
      "viewTransaction": "取引を表示",
      "rewardsClaimed": "報酬を請求しました！",
      "cosmicTokensYours": "あなたの宇宙トークンはあなたのものです！",
      "fetchError": "取得エラー",
      "loadingInfo": "プール情報を読み込み中...",
      "poolInfoUnavailable": "このプールのコメントセクションは利用できません。",
      "loadingProjectInfo": "ミーム情報を読み込み中...",
      "yourBalance": "あなたの残高",
      "staked": "ステーク済み",
      "maxSupply": "最大供給量",
      "stake": "ステーク",
      "unstake": "アンステーク",
      "stakePrompt": "トークンをステークして報酬を獲得し、プロジェクトをサポートしましょう！",
      "amountToStake": "ステークする金額",
      "max": "最大",
      "unstakePrompt": "ステーキングプールからトークンを引き出すには、アンステークしてください。",
      "amountToUnstake": "アンステークする金額",
      "confirmStake": "ステークを確認",
      "unstakeAll": "すべてアンステーク",
      "emergencyUnstakeInfo": "これは緊急アンステーキングトークンです。すべての資金を一度に引き出すことができます。",
      "confirmUnstake": "アンステークを確認",
      "yourStake": "あなたのステーク",
      "hodlNow": "HODL!!!",
      "hodlVaultDescription": "プロジェクトへのサポートを示し、信頼を築くためにトークンをHODLしてください。",
      "hodlVaultVesting": "ステークされたトークンは{count, plural, =1 {#ヶ月} other {#ヶ月}}の期間をかけて徐々にロック解除されます。ロック解除された部分はいつでも引き出すことができます。",
      "availableToStake": "ステーク可能",
      "totalStaked": "合計ステーク額",
      "availableToUnstake": "アンステーク可能",
      "collapseDetails": "詳細を折りたたむ",
      "expandDetails": "詳細を展開",
      "noDescription": "説明なし...ミームがそれを物語っているか、作成者が怠け者だったかのどちらかです。=)",
      "maxAvailable": "最大利用可能額",
      "processing": "処理中...",
      "stakeSuccessTitle": "ステーク成功",
      "unstakeSuccessTitle": "アンステーク成功",
      "emergencyUnstakeSuccessTitle": "緊急アンステーク成功",
      "unknownError": "不明なエラーが発生しました。",
      "ProjectNotFound": "ミームが見つかりません。",
      "stakingDuration": "HODL期間",
      "unstakePeriodMonths": "ヶ月",
      "hodlPeriod": "{count, plural, =1 {#ヶ月ロック} other {#ヶ月ロック}}",
      "dragAndDropOrClick": "ドラッグ＆ドロップまたはクリック",
      "selectTokenPrompt": "トークンを選択してください。",
      "fileTooLarge": "ファイルが大きすぎます（最大1MB）",
      "holdToSwitch": "{networkName}に切り替えるには{seconds}秒間長押ししてください",
      "testnetShort": "テストネット",
      "page": "ページ",
      "previous": "前へ",
      "next": "次へ",
      "noResultsFound": "結果が見つかりません。",
      "searching": "検索中",
      "networkMismatchError": "コメントするには{networkName}ネットワークに切り替えてください。",
      "allCategories": "すべて",
      "poolCompletedTitle": "プール完了",
      "poolCompletedSubtitle": "DEXに移行",
      "nameLabel": "名前",
      "congrats": "おめでとうございます",
      "coinBorn": "あなたのトークンが誕生しました",
      "migrationTitle": "移行完了",
      "migrationPanelDescription": "現在利用可能：",
      "runManualMigration": "移行を実行",
      "poolCompleted": "プール完了",
      "mainnetShort": "メインネット",
      "topHolders": "トップホルダー",
      "wallet": "ウォレット",
      "quantity": "数量",
      "noHoldersFound": "ホルダーが見つかりません。",
      "loadingChart": "チャートを読み込んでいます...",
      "chartError": "チャートデータの読み込み中にエラーが発生しました。",
      "copyAddress": "アドレスをコピー",
      "countdown": {
        "completed": "イベントが始まりました！",
        "days": "日",
        "hours": "時間",
        "minutes": "分",
        "seconds": "秒",
        "spikeyChamp": "Spikey Champ"
      },
      "popup": {
        "create_button": "作成",
        "sending_transaction": "トランザクションを送信中",
        "creating": "作成中...",
        "uploading_files": "メタデータをアップロード中",
        "uploading_image": "画像をアップロード中 (1/3)...",
        "uploading_metadata": "メタデータを保存中 (2/3)...",
        "polling_for_address": "アドレスを取得中",
        "creating_contract": "オンチェーンでプロジェクトを作成中 (3/3)...",
        "creationFee": "手数料: ${usd} (~{supra} SUPRA)"
      },
      "disclaimer": {
        "title": "警告！🚨 これはSpikey.funです — ウォール街ではありません。",
        "intro": "このプラットフォームはミーム、夢、そして退廃者でいっぱいです。ここでは誰でもトークンを立ち上げることができます。それにはあなたのおばあちゃん、あなたの犬、あるいは本物のハリネズミも含まれます。",
        "listTitle": "Spikey.funで作成されたトークンは次のとおりです：",
        "listItem1": "🧪 実験的",
        "listItem2": "🧻 非流動的",
        "listItem3": "🧠 しばしば愚か（しかし時には天才的）",
        "listItem4": "🦔 Spikey承認済み（冗談です、何も承認されていません）",
        "warning": "ここでトークンを買うのは野生のハリネズミを撫でるようなものです — 楽しいかもしれないし、刺されるかもしれません。",
        "dyor": "何かを触る前に、ご自身で調査（DYOR）してください。",
        "loseFunds": "資金を失った場合、Spikeyは悲しみますが、責任は負いません。",
        "winFunds": "あなたがミーム長者になった場合、Spikeyはあなたの鼻をツンと突くかもしれません。",
        "acceptButton": "理解し、同意します"
      },
      "retry": "再試行"
    },
    "wallets": {
      "connected": "接続済み",
      "title": "ウォレットを接続",
      "closeButtonLabel": "閉じる",
      "description": "続行するにはウォレットを接続してください"
    },
    "comments": {
      "title": "コメント",
      "addCommentPlaceholder": "コメントを追加...",
      "uploadMediaTitle": "画像/動画をアップロード",
      "posting": "投稿中...",
      "postButton": "投稿",
      "removeMediaTitle": "メディアを削除",
      "connectWalletError": "！ウォレットを接続してください！",
      "missingInfoError": "契約またはネットワーク情報がありません。",
      "emptyCommentError": "空のコメントは投稿できません。",
      "unknownError": "不明なエラーが発生しました。",
      "loading": "コメントを読み込み中...",
      "noComments": "まだコメントはありません。",
      "loadingInfo": "プール情報を読み込み中...",
      "poolInfoUnavailable": "このプールのコメントセクションは利用できません。",
      "fetchError": "コメントの取得中にエラーが発生しました",
      "nonceLoadErrorRetry": "検証データを読み込めませんでした。もう一度お試しください。",
      "connectWalletPrompt": "コメントするにはウォレットを接続してください",
      "signingFailedOrCancelled": "署名に失敗したか、キャンセルされました",
      "connectWallet": "ウォレットを接続",
      "connectToComment": "コメントするにはウォレットを接続してください",
      "likeCount": "{count, plural, =0 {0件のいいね} =1 {1件のいいね} other {#件のいいね}}",
      "beTheFirst": "最初にコメントする",
      "nonceFetchError": "ノンスの取得中にエラーが発生しました。後でもう一度お試しください。"
    },
    "Footer": {
      "brandName": "Spikey Corp",
      "copyright": "© {year} Spikey Corp. 無断複写・転載を禁じます。",
      "explore": "探検",
      "community": "コミュニティに参加",
      "whitepaper": "ホワイトペーパー",
      "terms": "利用規約",
      "privacy": "プライバシーポリシー",
      "secretTooltip": "これは何ですか？",
      "secretTooltip2": "続けてください...",
      "secretTooltip3": "もう一度！"
    }
}