{
  "Home": {
    "title": "🔥 MEME BURNER 🔥",
    "description": "Toss your meme into the burner and watch the flames incinerate it!",
    "selectMeme": "Select a Meme",
    "selectToken": "Select a token",
    "availableBalance": "Available Balance",
    "connectWallet": "Connect Wallet",
    "tokensToBurn": "Token:",
    "burning": "🔥 BURNING...",
    "burn": "🔥 BURN!",
    "Token": "Token",
    "BurnAmount": "Burn Amount",
    "loadingVault": "loading"
  },
  "TokenSelectorModal": {
    "selectToken": "Select a Token",
    "searchPlaceholder": "Search by name, symbol, or address",
    "loading": "Loading...",
    "error": "Error",
    "showOnlyVerified": "Show only verified",
    "unknownSymbol": "Unknown Symbol",
    "noTokensMatch": "No tokens match your criteria.",
    "closeModal": "Close modal",
    "showUnverifiedTokens": "Show unverified tokens",
    "noTokensFound": "No tokens found for '{searchTerm}'.",
    "noTokensAvailable": "No tokens available.",
    "couldNotFetchCustomToken": "Could not fetch custom token.",
    "tryEnablingUnverified": "Try enabling 'Show unverified tokens'.",
    "tokenIcon": "Token icon",
    "imageLoadError": "Error loading image from {iconSrc}",
    "unknownName": "Unknown Name",
    "unverified": "Unverified",
    "address": "Address",
    "type": "Type",
    "customFetched": "Custom fetched ({type})",
    "legacy": "Legacy",
    "previous": "Previous",
    "page": "Page {currentPage} of {totalPages}",
    "next": "Next",
    "configError": "Configuration error: Staking contract or module not set.",
    "coinLegacyError": "Error fetching Coin-Legacy metadata: {message}",
    "notFoundOrError": "Not found or error",
    "coinLegacyInvalidFormat": "Invalid Coin-Legacy metadata format.",
    "fungibleAssetError": "Error fetching Fungible Asset metadata: {message}",
    "fungibleAssetInvalidTypes": "Invalid Fungible Asset metadata types.",
    "fungibleAssetInvalidFormat": "Invalid Fungible Asset metadata format."
  },
  "wallets": {
    "connected": "Connected",
    "title": "Connect Wallet",
    "closeButtonLabel": "Close",
    "description": "Connect your wallet to continue"
  },
  "Footer": {
    "secretTooltip": "Click 3 times for a secret!",
    "secretTooltip2": "Almost there...",
    "secretTooltip3": "You found it!",
    "copyright": "© {year} MemeBurn. All rights reserved.",
    "terms": "Terms of Service",
    "privacy": "Privacy Policy",
    "whitepaper": "Whitepaper"
  },
  "BurnAmountInput": {
    "notAvailable": "N/A",
    "error": "Error",
    "balance": "Balance",
    "loading": "Loading...",
    "errorFetchingBalance": "Error fetching balance",
    "unknownError": "Unknown error"
  },
  "RewardAmountInput": {
    "notAvailable": "N/A",
    "error": "Error",
    "rewardsToDistribute": "Rewards to Distribute",
    "balance": "Balance",
    "loading": "Loading...",
    "errorFetchingBalance": "Error fetching balance",
    "unknownError": "Unknown error"
  },
  "TokenDisplayButton": {
    "tokenIconAlt": "Token icon",
    "imageLoadError": "Error loading image from {iconSrc}",
    "change": "Change",
    "selectToken": "Select {label}"
  },
  "translation": {
    "earn": "Earn",
    "souls": "Souls",
    "disconnect": "Disconnect",
    "connectWallet": "Connect Wallet",
    "loading": "Loading...",
    "getFreeSupra": "Get Free Supra",
    "selectToken": "Select Token",
    "selectButtonLabel": "Select",
    "selectTokenTitle": "Select Token",
    "countdown": {
      "completed": "The event is here!",
      "days": "Days",
      "hours": "Hours",
      "minutes": "Mins",
      "seconds": "Secs",
      "spikeyChamp": "Spikey Champ"
    }
  },
  "ForgeSoul": {
    "title": "Forge Soul",
    "description": "Forge your soul by burning tokens.",
    "communityEmberTitle": "Community Ember",
    "yourKindlingTitle": "Your Kindling",
    "mainTitle": "Fuel the Forge: The Meme Incinerator",
    "mainDescription": "Contribute tokens to the community pool, ignite them into flames, and earn Soulbound XP as proof of your sacrifice.",
    "captureSoul": "🔥 Forge Soul! 🔥",
    "forging": "Forging...",
    "copy": "Copy",
    "copied": "Copied!",
    "balance": "Balance",
    "amount": "Amount:",
    "Token": "Token",
    "selectSoulToken": "Select Token",
    "selectToken": "Select a Token",
    "loading": "Loading..."
  }
}